AUTHORS.rst
CONTRIBUTING.rst
HISTORY.rst
LICENSE
MANIFEST.in
README.rst
setup.cfg
setup.py
docs/Makefile
docs/authors.rst
docs/conf.py
docs/contributing.rst
docs/history.rst
docs/index.rst
docs/installation.rst
docs/make.bat
docs/readme.rst
docs/usage.rst
pyenvdiff/__init__.py
pyenvdiff/arg_parsing.py
pyenvdiff/client.py
pyenvdiff/collectors.py
pyenvdiff/compare.py
pyenvdiff/compat.py
pyenvdiff/custom_post.py
pyenvdiff/environment.py
pyenvdiff/hub.py
pyenvdiff/import_macros.py
pyenvdiff/info.py
pyenvdiff/post.py
pyenvdiff/post_to_hub.py
pyenvdiff/public_post.py
pyenvdiff/version.py
pyenvdiff.egg-info/PKG-INFO
pyenvdiff.egg-info/SOURCES.txt
pyenvdiff.egg-info/dependency_links.txt
pyenvdiff.egg-info/not-zip-safe
pyenvdiff.egg-info/top_level.txt
pyenvdiff/bottle/bottle.py
tests/__init__.py
tests/a.json
tests/b.json
tests/test_pyenvdiff.py