Metadata-Version: 1.1
Name: pyenvdiff
Version: 0.3.0
Summary: Python environment comparison tool.
Home-page: https://github.com/jnmclarty/pyenvdiff-lib
Author: Jeffrey McLarty
Author-email: jeffrey.mclarty@gmail.com
License: BSD license
Download-URL: https://github.com/jnmclarty/pyenvdiff-lib/tarball/0.3.0
Keywords: pyenvdiff
Platform: UNKNOWN
Classifier: Development Status :: 3 - Alpha
Classifier: Intended Audience :: Developers
Classifier: License :: OSI Approved :: BSD License
Classifier: Natural Language :: English
Classifier: Programming Language :: Python :: 2
Classifier: Programming Language :: Python :: 3
Classifier: Programming Language :: Python :: 3.3
Classifier: Programming Language :: Python :: 3.4
Classifier: Programming Language :: Python :: 3.5
Classifier: Programming Language :: Python :: 3.6
Classifier: Programming Language :: Python :: 3.7
Classifier: Operating System :: OS Independent
